jucombinator-0.3.0.dist-info/METADATA
jucombinator-0.3.0.dist-info/WHEEL
jucombinator/__init__.py
jucombinator/py.typed
jucombinator/jucombinator.pyi
jucombinator/jucombinator.cpython-312-aarch64-linux-gnu.so
jucombinator-0.3.0.dist-info/RECORD
